mazes/__init__.py
mazes/cli.py
mazes/maze.py
mazes/store.py
Mazes-0.2.1.dist-info/METADATA
Mazes-0.2.1.dist-info/WHEEL
Mazes-0.2.1.dist-info/entry_points.txt
Mazes-0.2.1.dist-info/top_level.txt
Mazes-0.2.1.dist-info/RECORD
