Metadata-Version: 2.1
Name: Mazes
Version: 0.2.1
Summary: Generates and solves rectangular mazes in the terminal. Comes with Python API.
Home-page: https://github.com/GrandMoff100/Mazes
Author: GrandMoff100
Author-email: nlarsen23.student@gmail.com
License: UNKNOWN
Platform: UNKNOWN
Requires-Dist: colorama
Requires-Dist: termcolor
